CHANGES.txt
LICENSE.txt
README.txt
setup.py
src/getpaid/__init__.py
src/getpaid.wizard.egg-info/PKG-INFO
src/getpaid.wizard.egg-info/SOURCES.txt
src/getpaid.wizard.egg-info/dependency_links.txt
src/getpaid.wizard.egg-info/namespace_packages.txt
src/getpaid.wizard.egg-info/not-zip-safe
src/getpaid.wizard.egg-info/requires.txt
src/getpaid.wizard.egg-info/top_level.txt
src/getpaid/wizard/__init__.py
src/getpaid/wizard/_wizard.py
src/getpaid/wizard/interfaces.py