Metadata-Version: 1.0
Name: getpaid.wizard
Version: 0.4
Summary: Sequence composition of views, viewlets, forms.
Home-page: UNKNOWN
Author: Kapil Thangavelu
Author-email: kapil.foss@gmail.com
License: X11
Keywords: zope zope3
Platform: UNKNOWN
Classifier: Framework :: Plone
Classifier: Programming Language :: Python
Classifier: Framework :: Zope3
Classifier: Intended Audience :: Developers
Classifier: License :: OSI Approved :: Zope Public License
Classifier: Operating System :: OS Independent
Classifier: Topic :: Office/Business :: Financial
Classifier: Topic :: Software Development :: Libraries
